transfa/__init__.py
transfa/api_client.py
transfa/api_resources/__init__.py
transfa/api_resources/payments.py
transfa/api_resources/webhook.py
transfa/configs/__init__.py
transfa/configs/version.py
transfa/types/__init__.py
transfa/types/enums.py
transfa/utils/__init__.py
transfa/utils/helpers.py
transfa-0.2.6.dist-info/LICENSE
transfa-0.2.6.dist-info/METADATA
transfa-0.2.6.dist-info/WHEEL
transfa-0.2.6.dist-info/top_level.txt
transfa-0.2.6.dist-info/RECORD
