Metadata-Version: 2.1
Name: transfa
Version: 0.2.6
Summary: This is the official python SDK for the Transfa API.
Home-page: https://transfapp.com
Author: Kolawole Mangabo
Author-email: kolawole.mangabo@transfapp.com
License: MIT
Classifier: Development Status :: 5 - Production/Stable
Classifier: Intended Audience :: Developers
Classifier: License :: OSI Approved :: MIT License
Classifier: Operating System :: OS Independent
Classifier: Programming Language :: Python
Classifier: Programming Language :: Python :: 3.8
Classifier: Programming Language :: Python :: 3.9
Classifier: Programming Language :: Python :: 3.10
Classifier: Programming Language :: Python :: Implementation :: PyPy
Classifier: Topic :: Software Development :: Libraries :: Python Modules
License-File: LICENSE
Requires-Dist: requests >=2.20
Provides-Extra: test
Requires-Dist: pytest ; extra == 'test'
Requires-Dist: responses ; extra == 'test'
Requires-Dist: coverage ; extra == 'test'
